s2t/__init__.py
s2t/cli.py
s2t/config.py
s2t/outputs.py
s2t/py.typed
s2t/recorder.py
s2t/types.py
s2t/utils.py
s2t/whisper_engine.py
s2t/translator/__init__.py
s2t/translator/argos_backend.py
s2t-0.2.2.dist-info/METADATA
s2t-0.2.2.dist-info/WHEEL
s2t-0.2.2.dist-info/entry_points.txt
s2t-0.2.2.dist-info/top_level.txt
s2t-0.2.2.dist-info/RECORD
