Metadata-Version: 2.4
Name: s2t
Version: 0.2.2
Summary: Speech to Text (s2t): Record audio, run Whisper, export formats, and copy transcript to clipboard.
Author: Maintainers
License-Expression: LicenseRef-Proprietary
Classifier: Programming Language :: Python :: 3
Classifier: Programming Language :: Python :: 3 :: Only
Classifier: Programming Language :: Python :: 3.11
Classifier: Programming Language :: Python :: 3.12
Classifier: Environment :: Console
Classifier: Operating System :: OS Independent
Requires-Python: <3.13,>=3.11
Requires-Dist: sounddevice>=0.4.6
Requires-Dist: soundfile>=0.12.1
Requires-Dist: numpy>=1.23
Requires-Dist: openai-whisper>=20231117
Requires-Dist: argostranslate>=1.9.0
Provides-Extra: dev
Requires-Dist: pytest>=7; extra == "dev"
Requires-Dist: pytest-cov>=4; extra == "dev"
Requires-Dist: ruff>=0.4; extra == "dev"
Requires-Dist: mypy>=1.7; extra == "dev"
Requires-Dist: build>=1; extra == "dev"
Requires-Dist: setuptools-scm>=8; extra == "dev"
Requires-Dist: twine>=4; extra == "dev"
Provides-Extra: translate
Requires-Dist: argostranslate>=1.9.0; extra == "translate"
